{
  "audiovisual_files": {
    "04b67036-8208-4ea8-8156-80f67f4366d1": {
      "label": "Radiolab Driverless Dilemma",
      "is_offline": false,
      "file_url": "https://waaa.wnyc.org/758af4c0-a2c3-47ec-a2d8-05f41bfbde51/episodes/46262cab-824d-43f8-9044-839c620ef092/audio/128/default.mp3/default.mp3_ywr3ahjkcgo_573a80f0c1f1a9a2409c754cdfacffc5_42264561.mp3?awCollectionId=758af4c0-a2c3-47ec-a2d8-05f41bfbde51&awEpisodeId=46262cab-824d-43f8-9044-839c620ef092&hash_redirect=1&x-total-bytes=42264561&x-ais-classified=streaming&listeningSessionID=0CD_382_22__422ae629a0d6c5c3eba08294309aaee091775c57",
      "duration": 2639
    }
  },
  "auto_generate_web_page": true,
  "item_type": "Audio",
  "label": "Annotating Radiolab's \"Driverless Dilemma\"",
  "created_at": "2025-01-23T19:05:30.833Z",
  "created_by": "saamturner",
  "updated_at": "2025-01-28T23:55:55.738Z",
  "updated_by": "saamturner",
  "description": [
    {
      "type": "paragraph",
      "children": [
        {
          "text": "Below you'll find a media player featuring Radiolab's \"Driverless Dilemma\" podcast episode and my annotations on the podcast. You can navigate the annotations in a few different ways: "
        }
      ]
    },
    {
      "type": "numbered-list",
      "children": [
        {
          "type": "list-item",
          "children": [
            {
              "text": "Play the audio and follow along as the annotations auto-scroll according to the timestamps, "
            }
          ]
        },
        {
          "type": "list-item",
          "children": [
            {
              "text": "Filter the annotations by their tags and categories to view specific annotations (e.g., select \"Rhetorical Situation\" to see all annotations about this group of tags, or select an individual tag, like \"ethos,\" to only view moments tagged as \"ethos\"), and "
            }
          ]
        },
        {
          "type": "list-item",
          "children": [
            {
              "text": "Use the search bar to search terms in the annotations. "
            }
          ]
        }
      ]
    },
    {
      "type": "paragraph",
      "children": [
        {
          "text": "You can also explore my annotations by navigating to the project's Index, which will visualize all of the tags and categories across the media. "
        }
      ]
    }
  ]
}